src/__init__.py
lamini_client-0.0.1.dist-info/LICENSE
lamini_client-0.0.1.dist-info/METADATA
lamini_client-0.0.1.dist-info/WHEEL
lamini_client-0.0.1.dist-info/top_level.txt
lamini_client-0.0.1.dist-info/RECORD
